nonebot_plugin_perithacus/__init__.py
nonebot_plugin_perithacus/apscheduler.py
nonebot_plugin_perithacus/cmd_add.py
nonebot_plugin_perithacus/cmd_check.py
nonebot_plugin_perithacus/cmd_delete.py
nonebot_plugin_perithacus/cmd_detail.py
nonebot_plugin_perithacus/cmd_edit.py
nonebot_plugin_perithacus/cmd_list.py
nonebot_plugin_perithacus/cmd_search.py
nonebot_plugin_perithacus/command.py
nonebot_plugin_perithacus/database.py
nonebot_plugin_perithacus/handle_args.py
nonebot_plugin_perithacus/lib.py
nonebot_plugin_perithacus/migrations/4184a6a150e9_.py
nonebot_plugin_perithacus/migrations/59488f45afb7_.py
nonebot_plugin_perithacus/migrations/bd67704f77ad_.py
nonebot_plugin_perithacus/migrations/c2cbe27dd921_.py
nonebot_plugin_perithacus/migrations/cc658325e0ad_.py
nonebot_plugin_perithacus/trigger.py
nonebot_plugin_perithacus/upgrade_database.py
nonebot_plugin_perithacus-1.4.0.dist-info/WHEEL
nonebot_plugin_perithacus-1.4.0.dist-info/METADATA
nonebot_plugin_perithacus-1.4.0.dist-info/RECORD
