Metadata-Version: 2.4
Name: nonebot-plugin-pErithacus
Version: 1.4.0
Summary: pErithacus 是一个基于 NoneBot2 框架的聊天插件，可以根据用户设定的关键词自动回复相关内容。该插件提供了完整的词条管理功能，让用户能够轻松创建、编辑和管理自定义回复内容
Keywords: nonebot2,chatbot,qqbot,nonebot-plugin
Author: SnowMoonSS
License-Expression: MIT
Classifier: Programming Language :: Python :: 3
Classifier: Programming Language :: Python :: 3.14
Classifier: Operating System :: OS Independent
Classifier: Framework :: Robot Framework
Requires-Dist: httpx>=0.24.0
Requires-Dist: filetype>=1.2.0
Requires-Dist: nonebot2>=2.4.4
Requires-Dist: nonebot-plugin-localstore>=0.7.4
Requires-Dist: nonebot-plugin-alconna>=0.60.3
Requires-Dist: nonebot-plugin-orm[default]>=0.8.2
Requires-Dist: nonebot-plugin-apscheduler>=0.5.0
Requires-Dist: pyright[nodejs] ; extra == 'dev'
Requires-Dist: ruff ; extra == 'dev'
Requires-Python: >=3.12, <4.0
Project-URL: Homepage, https://github.com/SnowMoonSS/nonebot-plugin-pErithacus
Project-URL: Repository, https://github.com/SnowMoonSS/nonebot-plugin-pErithacus.git
Project-URL: Documentation, https://github.com/SnowMoonSS/nonebot-plugin-pErithacus/blob/master/README.md
Project-URL: Issues, https://github.com/SnowMoonSS/nonebot-plugin-pErithacus/issues
Provides-Extra: dev
